strappy/__init__.py
strappy/container.py
strappy/errors.py
strappy/protocols.py
strappy/provider.py
strappy/strategies.py
strappy/type_utils.py
strappy_di-0.2.0.dist-info/LICENSE
strappy_di-0.2.0.dist-info/METADATA
strappy_di-0.2.0.dist-info/WHEEL
strappy_di-0.2.0.dist-info/top_level.txt
strappy_di-0.2.0.dist-info/RECORD
