Metadata-Version: 2.1
Name: strappy-di
Version: 0.2.0
Summary: Light, flexible, and pythonic dependency injection framework
Author-email: Caroline Matson <carlymatson21@gmail.com>
License: MIT License
Project-URL: homepage, https://github.com/carlymatson/strappy-di
Keywords: dependency,injection,bootstrap
Classifier: License :: OSI Approved :: MIT License
Classifier: Programming Language :: Python
Classifier: Programming Language :: Python :: 3
Requires-Python: >=3.11
License-File: LICENSE
